mkdocs_statistics_plugin/__init__.py
mkdocs_statistics_plugin/plugin.py
mkdocs_statistics_plugin/templates/page_statistics.html
mkdocs_statistics_plugin-0.1.5.dist-info/LICENSE
mkdocs_statistics_plugin-0.1.5.dist-info/METADATA
mkdocs_statistics_plugin-0.1.5.dist-info/WHEEL
mkdocs_statistics_plugin-0.1.5.dist-info/entry_points.txt
mkdocs_statistics_plugin-0.1.5.dist-info/top_level.txt
mkdocs_statistics_plugin-0.1.5.dist-info/RECORD
