Metadata-Version: 2.1
Name: mkdocs-statistics-plugin
Version: 0.1.5
Summary: A MkDocs plugin that generate statistic data of a site
Home-page: https://github.com/TonyCrane/mkdocs-statistics-plugin
Author: TonyCrane
Author-email: me@tonycrane.cc
License: MIT
Keywords: mkdocs python markdown statistics
Classifier: Development Status :: 3 - Alpha
Classifier: Intended Audience :: Developers
Classifier: Intended Audience :: Information Technology
Classifier: License :: OSI Approved :: MIT License
Classifier: Programming Language :: Python
Classifier: Programming Language :: Python :: 3.5
Classifier: Programming Language :: Python :: 3.6
Classifier: Programming Language :: Python :: 3.7
Classifier: Programming Language :: Python :: 3.8
Classifier: Programming Language :: Python :: 3.9
Classifier: Programming Language :: Python :: 3.10
Requires-Python: >=3.5
License-File: LICENSE
Requires-Dist: mkdocs
